maque/SKILL.md
maque/__init__.py
maque/__main__.py
maque/constant.py
maque/core.py
maque/ai_platform/__init__.py
maque/ai_platform/crawl.py
maque/ai_platform/metrics.py
maque/ai_platform/nlp_preprocess.py
maque/ai_platform/webpage_screen_shot.py
maque/algorithms/__init__.py
maque/algorithms/bezier.py
maque/algorithms/bktree.py
maque/algorithms/core.py
maque/algorithms/hilbert.py
maque/algorithms/rate_function.py
maque/algorithms/transform.py
maque/algorithms/trie.py
maque/algorithms/utils.py
maque/algorithms/video.py
maque/api/__init__.py
maque/api/common.py
maque/api/fetch.py
maque/api/static/icon.png
maque/api/static/redoc.standalone.js
maque/api/static/swagger-ui-bundle.js
maque/api/static/swagger-ui.css
maque/cli/__init__.py
maque/cli/clean_invisible_chars.py
maque/cli/core.py
maque/cli/mllm_run.py
maque/cli/script.py
maque/cli/skill.py
maque/cli/tree.py
maque/cli/groups/__init__.py
maque/cli/groups/config.py
maque/cli/groups/data.py
maque/cli/groups/doctor.py
maque/cli/groups/embedding.py
maque/cli/groups/git.py
maque/cli/groups/help.py
maque/cli/groups/llm.py
maque/cli/groups/mllm.py
maque/cli/groups/mllm_simple.py
maque/cli/groups/quant.py
maque/cli/groups/service.py
maque/cli/groups/system.py
maque/clustering/__init__.py
maque/clustering/analyzer.py
maque/clustering/clusterers.py
maque/clustering/sampler.py
maque/clustering/visualizer.py
maque/cv/__init__.py
maque/cv/image.py
maque/cv/utils.py
maque/cv/video/__init__.py
maque/cv/video/keyframe_extractor.py
maque/data/__init__.py
maque/data/tmux/.tmux.conf
maque/data/tmux/.tmux.conf.local
maque/data/tmux/__init__.py
maque/data/vim/.vimrc
maque/data/vim/__init__.py
maque/embedding/__init__.py
maque/embedding/base.py
maque/embedding/multimodal.py
maque/embedding/server.py
maque/embedding/text.py
maque/git/__init__.py
maque/git/pure_git.py
maque/io/__init__.py
maque/io/core.py
maque/io/ops.py
maque/llm/__init__.py
maque/llm/backend.py
maque/llm/base.py
maque/llm/server.py
maque-0.2.11.dist-info/METADATA
maque-0.2.11.dist-info/WHEEL
maque-0.2.11.dist-info/entry_points.txt
maque-0.2.11.dist-info/licenses/LICENSE
maque-0.2.11.dist-info/RECORD
